odoo/addons/sale_order_line_stock_move_history/README.rst
odoo/addons/sale_order_line_stock_move_history/__init__.py
odoo/addons/sale_order_line_stock_move_history/__manifest__.py
odoo/addons/sale_order_line_stock_move_history/i18n/es.po
odoo/addons/sale_order_line_stock_move_history/i18n/it.po
odoo/addons/sale_order_line_stock_move_history/i18n/sale_order_line_stock_move_history.pot
odoo/addons/sale_order_line_stock_move_history/models/__init__.py
odoo/addons/sale_order_line_stock_move_history/models/sale_order_line.py
odoo/addons/sale_order_line_stock_move_history/readme/CONTRIBUTORS.md
odoo/addons/sale_order_line_stock_move_history/readme/DESCRIPTION.md
odoo/addons/sale_order_line_stock_move_history/readme/USAGE.md
odoo/addons/sale_order_line_stock_move_history/static/description/icon.png
odoo/addons/sale_order_line_stock_move_history/static/description/index.html
odoo/addons/sale_order_line_stock_move_history/views/sale_order_views.xml
odoo/addons/sale_order_line_stock_move_history/views/stock_move_views.xml
odoo_addon_sale_order_line_stock_move_history-18.0.1.0.0.3.dist-info/METADATA
odoo_addon_sale_order_line_stock_move_history-18.0.1.0.0.3.dist-info/WHEEL
odoo_addon_sale_order_line_stock_move_history-18.0.1.0.0.3.dist-info/top_level.txt
odoo_addon_sale_order_line_stock_move_history-18.0.1.0.0.3.dist-info/RECORD
